{
"type": "FeatureCollection",
"name": "Chasepoint",
"crs": { "type": "name", "properties": { "name": "urn:ogc:def:crs:OGC:1.3:CRS84" } },
"features": [
{ "type": "Feature", "properties": { "id": null, "name": "Chase Dining Hall" }, "geometry": { "type": "Point", "coordinates": [ -79.045618733196989, 35.905969849104004 ] } }
]
}
